{
  "relatedQuestions": [
    {
      "relatedQuestionStrings": {
        "en": null,
        "de": "Möchten Sie in den nächsten fünf Jahren Ihrer Studienqualifikation entsprechend erwerbstätig sein?"
      },
      "questionNumber": "1.3",
      "instrumentNumber": 2
    }
  ],
  "distribution": {
    "statistics": {
      "meanDeviation": 0,
      "mode": "1",
      "highWhisker": 3.5,
      "lowWhisker": 1,
      "thirdQuartile": "2",
      "firstQuartile": "1",
      "standardDeviation": null,
      "median": "1",
      "kurtosis": null,
      "skewness": null,
      "maximum": "5",
      "minimum": "1",
      "meanValue": null
    },
    "missings": [
      {
        "label": {
          "en": "no answer",
          "de": "keine Angabe"
        },
        "relativeFrequency": 0.68,
        "absoluteFrequency": 11,
        "code": -998
      },
      {
        "label": {
          "en": "not participated (panel)",
          "de": "keine Teilnahme (Panel)"
        },
        "relativeFrequency": 50.86,
        "absoluteFrequency": 825,
        "code": -995
      }
    ],
    "validResponses": [
      {
        "label": {
          "en": "Definitely",
          "de": "auf jeden Fall"
        },
        "validRelativeFrequency": 63.74,
        "relativeFrequency": 30.89,
        "absoluteFrequency": 501,
        "value": "1"
      },
      {
        "label": {
          "en": null,
          "de": "2"
        },
        "validRelativeFrequency": 24.05,
        "relativeFrequency": 11.65,
        "absoluteFrequency": 189,
        "value": "2"
      },
      {
        "label": {
          "en": null,
          "de": "3"
        },
        "validRelativeFrequency": 8.4,
        "relativeFrequency": 4.07,
        "absoluteFrequency": 66,
        "value": "3"
      },
      {
        "label": {
          "en": null,
          "de": "4"
        },
        "validRelativeFrequency": 2.42,
        "relativeFrequency": 1.17,
        "absoluteFrequency": 19,
        "value": "4"
      },
      {
        "label": {
          "en": "Definitely not",
          "de": "auf keinen Fall"
        },
        "validRelativeFrequency": 1.4,
        "relativeFrequency": 0.68,
        "absoluteFrequency": 11,
        "value": "5"
      }
    ],
    "totalValidRelativeFrequency": 48.46,
    "totalValidAbsoluteFrequency": 786,
    "totalAbsoluteFrequency": 1622
  },
  "filterDetails": {
    "expressionLanguage": null,
    "description": {
      "en": null,
      "de": null
    },
    "expression": null
  },
  "generationDetails": {
    "ruleExpressionLanguage": null,
    "rule": null,
    "description": {
      "en": null,
      "de": null
    }
  },
  "storageType": "double",
  "relatedVariables": null,
  "doNotDisplayThousandsSeparator": false,
  "derivedVariablesIdentifier": null,
  "panelIdentifier": null,
  "surveyNumbers": [4],
  "indexInDataSet": 693,
  "accessWays": ["download-cuf", "download-suf", "remote-desktop-suf", "onsite-suf"],
  "annotations": {
    "en": null,
    "de": null
  },
  "label": {
    "en": "employment next 5 years",
    "de": "Erwerbstätigkeit nächste 5 Jahre"
  },
  "scaleLevel": {
    "en": "ordinal",
    "de": "ordinal"
  },
  "dataType": {
    "en": "numeric",
    "de": "numerisch"
  }
}
