{
  "relatedQuestions": [
    {
      "relatedQuestionStrings": {
        "en": null,
        "de": "Wie zufrieden sind Sie mit Ihrer derzeitigen  (bzw. zuletzt ausgeübten) Beschäftigung?\r\nArbeitsplatzsicherheit"
      },
      "questionNumber": "5.13",
      "instrumentNumber": 1
    }
  ],
  "distribution": {
    "statistics": {
      "meanDeviation": 1.4826,
      "mode": "2",
      "highWhisker": 4.5,
      "lowWhisker": 1,
      "thirdQuartile": "3",
      "firstQuartile": "2",
      "standardDeviation": null,
      "median": "2",
      "kurtosis": null,
      "skewness": null,
      "maximum": "5",
      "minimum": "1",
      "meanValue": null
    },
    "missings": [
      {
        "label": {
          "en": "no answer",
          "de": null
        },
        "relativeFrequency": 14.12,
        "absoluteFrequency": 229,
        "code": -998
      },
      {
        "label": {
          "en": "filtered",
          "de": null
        },
        "relativeFrequency": 45.38,
        "absoluteFrequency": 736,
        "code": -989
      }
    ],
    "validResponses": [
      {
        "label": {
          "en": "To a high degree",
          "de": null
        },
        "validRelativeFrequency": 18.11,
        "relativeFrequency": 7.34,
        "absoluteFrequency": 119,
        "value": "1"
      },
      {
        "label": {
          "en": null,
          "de": null
        },
        "validRelativeFrequency": 32.12,
        "relativeFrequency": 13.01,
        "absoluteFrequency": 211,
        "value": "2"
      },
      {
        "label": {
          "en": null,
          "de": null
        },
        "validRelativeFrequency": 25.57,
        "relativeFrequency": 10.36,
        "absoluteFrequency": 168,
        "value": "3"
      },
      {
        "label": {
          "en": null,
          "de": null
        },
        "validRelativeFrequency": 11.42,
        "relativeFrequency": 4.62,
        "absoluteFrequency": 75,
        "value": "4"
      },
      {
        "label": {
          "en": "Not at all",
          "de": null
        },
        "validRelativeFrequency": 12.79,
        "relativeFrequency": 5.18,
        "absoluteFrequency": 84,
        "value": "5"
      }
    ],
    "totalValidRelativeFrequency": 40.51,
    "totalValidAbsoluteFrequency": 657,
    "totalAbsoluteFrequency": 1622
  },
  "filterDetails": {
    "expressionLanguage": "Stata",
    "description": {
      "en": null,
      "de": null
    },
    "expression": "if aocc18==1"
  },
  "generationDetails": {
    "ruleExpressionLanguage": null,
    "rule": null,
    "description": {
      "en": null,
      "de": null
    }
  },
  "storageType": "double",
  "relatedVariables": null,
  "doNotDisplayThousandsSeparator": false,
  "derivedVariablesIdentifier": null,
  "repeatedMeasurementIdentifier": "gra2005-ds3-occ33h",
  "surveyNumbers": [3],
  "indexInDataSet": 622,
  "accessWays": ["download-cuf", "download-suf", "remote-desktop-suf", "onsite-suf"],
  "annotations": {
    "en": null,
    "de": null
  },
  "label": {
    "en": "contentment with occupation: job security",
    "de": null
  },
  "scaleLevel": {
    "en": "ordinal",
    "de": "ordinal"
  },
  "dataType": {
    "en": "numeric",
    "de": "numerisch"
  }
}
