{
  "relatedQuestions": [
    {
      "relatedQuestionStrings": {
        "en": null,
        "de": "Wie wichtig sind die folgenden Kenntnisse und Fähigkeiten für Ihre derzeitige (bzw. letzte, wenn Sie nicht berufstätig sind) berufliche Tätigkeit (Spalte A)? In welchem Maße verfügen Sie heute über diese Kennt nisse und Fähigkeiten (Spalte B)?\r\nIch verfüge heute darüber …\r\nKenntnisse in EDV"
      },
      "questionNumber": "1.8",
      "instrumentNumber": 2
    }
  ],
  "distribution": {
    "statistics": {
      "meanDeviation": 1.4826,
      "mode": "2",
      "highWhisker": 3.5,
      "lowWhisker": 1,
      "thirdQuartile": "2",
      "firstQuartile": "1",
      "standardDeviation": null,
      "median": "2",
      "kurtosis": null,
      "skewness": null,
      "maximum": "4",
      "minimum": "1",
      "meanValue": null
    },
    "missings": [
      {
        "label": {
          "en": null,
          "de": "keine Angabe"
        },
        "relativeFrequency": 0.8,
        "absoluteFrequency": 13,
        "code": -998
      },
      {
        "label": {
          "en": null,
          "de": "keine Teilnahme (Panel)"
        },
        "relativeFrequency": 50.86,
        "absoluteFrequency": 825,
        "code": -995
      }
    ],
    "validResponses": [
      {
        "label": {
          "en": null,
          "de": "in hohem Maße"
        },
        "validRelativeFrequency": 38.52,
        "relativeFrequency": 18.62,
        "absoluteFrequency": 302,
        "value": "1"
      },
      {
        "label": {
          "en": null,
          "de": "2"
        },
        "validRelativeFrequency": 44.77,
        "relativeFrequency": 21.64,
        "absoluteFrequency": 351,
        "value": "2"
      },
      {
        "label": {
          "en": null,
          "de": "3"
        },
        "validRelativeFrequency": 15.31,
        "relativeFrequency": 7.4,
        "absoluteFrequency": 120,
        "value": "3"
      },
      {
        "label": {
          "en": null,
          "de": "4"
        },
        "validRelativeFrequency": 1.4,
        "relativeFrequency": 0.68,
        "absoluteFrequency": 11,
        "value": "4"
      }
    ],
    "totalValidRelativeFrequency": 48.34,
    "totalValidAbsoluteFrequency": 784,
    "totalAbsoluteFrequency": 1622
  },
  "filterDetails": {
    "expressionLanguage": null,
    "description": {
      "en": null,
      "de": null
    },
    "expression": null
  },
  "generationDetails": {
    "ruleExpressionLanguage": null,
    "rule": null,
    "description": {
      "en": null,
      "de": null
    }
  },
  "storageType": "integer",
  "relatedVariables": null,
  "doNotDisplayThousandsSeparator": false,
  "derivedVariablesIdentifier": null,
  "panelIdentifier": null,
  "surveyNumbers": [4],
  "indexInDataSet": 745,
  "accessWays": ["download-cuf", "download-suf", "remote-desktop-suf", "onsite-suf"],
  "annotations": {
    "en": null,
    "de": null
  },
  "label": {
    "en": null,
    "de": "vorhanden: EDV-Kenntnisse"
  },
  "scaleLevel": {
    "en": "ordinal",
    "de": "ordinal"
  },
  "dataType": {
    "en": "numeric",
    "de": "numerisch"
  }
}
